eboot/.DS_Store
eboot/__init__.py
eboot/Configuration.py
eboot/gtest2html/__init__.py
eboot/gtest2html/ConvertTestReport.py
eboot/gtest2html/CreateTestReports.py
eboot/gtest2html/gtest2html.py
eboot/main.py
eboot/RootCMakelist.py
eboot/utils.py
eboot-1.0.dist-info/entry_points.txt
eboot-1.0.dist-info/METADATA
eboot-1.0.dist-info/WHEEL
eboot-1.0.dist-info/RECORD
