Metadata-Version: 2.1
Name: eboot
Version: 1.0
Summary: 
Author: qiuyeyijian
Author-email: zlw9821@qq.com
Requires-Python: >=3.7,<4.0
Classifier: Programming Language :: Python :: 3
Classifier: Programming Language :: Python :: 3.7
Classifier: Programming Language :: Python :: 3.8
Classifier: Programming Language :: Python :: 3.9
Classifier: Programming Language :: Python :: 3.10
Classifier: Programming Language :: Python :: 3.11
Requires-Dist: rich (>=12.6.0,<13.0.0)
Requires-Dist: typer[all] (>=0.7.0,<0.8.0)
